[
  {
    "timestamp": "2026-01-27T10:56:16.276610Z",
    "market_id": "119872",
    "question": "2026 Men's Australian Open Winner",
    "from_regime": "High Confidence",
    "to_regime": "Active",
    "metrics_snapshot": {
      "nexus_score": 76.9,
      "macro_sensitivity": 0.0
    }
  },
  {
    "timestamp": "2026-01-27T10:27:09.269948Z",
    "market_id": "30828",
    "question": "Xi Jinping out before 2027?",
    "from_regime": "High Confidence",
    "to_regime": "Active",
    "metrics_snapshot": {
      "nexus_score": 79.2,
      "macro_sensitivity": 0.0
    }
  },
  {
    "timestamp": "2026-01-27T10:27:09.269948Z",
    "market_id": "31552",
    "question": "Presidential Election Winner 2028",
    "from_regime": "High Confidence",
    "to_regime": "Active",
    "metrics_snapshot": {
      "nexus_score": 77.9,
      "macro_sensitivity": 0.0
    }
  },
  {
    "timestamp": "2026-01-27T09:49:17.573131Z",
    "market_id": "151953",
    "question": "US/Israel strikes Iran by...?",
    "from_regime": "Active",
    "to_regime": "Low Confidence",
    "metrics_snapshot": {
      "nexus_score": 43.2,
      "macro_sensitivity": 0.0
    }
  },
  {
    "timestamp": "2026-01-27T09:05:19.480601Z",
    "market_id": "119872",
    "question": "2026 Men's Australian Open Winner",
    "from_regime": "Active",
    "to_regime": "High Confidence",
    "metrics_snapshot": {
      "nexus_score": 81.5,
      "macro_sensitivity": 0.0
    }
  },
  {
    "timestamp": "2026-01-27T09:05:19.480601Z",
    "market_id": "84841",
    "question": "Epstein blackmail evidence released by...? ",
    "from_regime": "Active",
    "to_regime": "High Confidence",
    "metrics_snapshot": {
      "nexus_score": 80.0,
      "macro_sensitivity": 0.0
    }
  },
  {
    "timestamp": "2026-01-27T08:32:32.158926Z",
    "market_id": "50282",
    "question": "Oscars 2026: Best Actor Winner",
    "from_regime": "Active",
    "to_regime": "High Confidence",
    "metrics_snapshot": {
      "nexus_score": 82.4,
      "macro_sensitivity": 0.0
    }
  },
  {
    "timestamp": "2026-01-27T08:32:32.158926Z",
    "market_id": "125868",
    "question": "Will Silver (SI) hit__ by end of January?",
    "from_regime": "Active",
    "to_regime": "Volatile",
    "metrics_snapshot": {
      "nexus_score": 48.7,
      "macro_sensitivity": 0.0
    }
  },
  {
    "timestamp": "2026-01-27T08:32:32.158926Z",
    "market_id": "119872",
    "question": "2026 Men's Australian Open Winner",
    "from_regime": "High Confidence",
    "to_regime": "Active",
    "metrics_snapshot": {
      "nexus_score": 78.8,
      "macro_sensitivity": 0.0
    }
  },
  {
    "timestamp": "2026-01-27T08:32:32.158926Z",
    "market_id": "31552",
    "question": "Presidential Election Winner 2028",
    "from_regime": "Active",
    "to_regime": "High Confidence",
    "metrics_snapshot": {
      "nexus_score": 80.2,
      "macro_sensitivity": 0.0
    }
  },
  {
    "timestamp": "2026-01-27T07:56:32.437441Z",
    "market_id": "89502",
    "question": "What price will Bitcoin hit in 2026?",
    "from_regime": "Low Confidence",
    "to_regime": "Active",
    "metrics_snapshot": {
      "nexus_score": 50.9,
      "macro_sensitivity": 0.0
    }
  },
  {
    "timestamp": "2026-01-27T07:56:32.437441Z",
    "market_id": "31552",
    "question": "Presidential Election Winner 2028",
    "from_regime": "High Confidence",
    "to_regime": "Active",
    "metrics_snapshot": {
      "nexus_score": 79.9,
      "macro_sensitivity": 0.0
    }
  },
  {
    "timestamp": "2026-01-27T07:05:18.631470Z",
    "market_id": "119872",
    "question": "2026 Men's Australian Open Winner",
    "from_regime": "Active",
    "to_regime": "High Confidence",
    "metrics_snapshot": {
      "nexus_score": 80.5,
      "macro_sensitivity": 0.0
    }
  },
  {
    "timestamp": "2026-01-26T23:57:49.428506Z",
    "market_id": "31552",
    "question": "Presidential Election Winner 2028",
    "from_regime": "Active",
    "to_regime": "High Confidence",
    "metrics_snapshot": {
      "nexus_score": 80.7,
      "macro_sensitivity": 0.0
    }
  },
  {
    "timestamp": "2026-01-26T23:45:34.859952Z",
    "market_id": "80505",
    "question": "US government shutdown Saturday?",
    "from_regime": "Active",
    "to_regime": "High Confidence",
    "metrics_snapshot": {
      "nexus_score": 80.0,
      "macro_sensitivity": 0.0
    }
  },
  {
    "timestamp": "2026-01-26T22:48:32.730459Z",
    "market_id": "30615",
    "question": "2026 FIFA World Cup Winner ",
    "from_regime": "Active",
    "to_regime": "High Confidence",
    "metrics_snapshot": {
      "nexus_score": 80.3,
      "macro_sensitivity": 0.0
    }
  },
  {
    "timestamp": "2026-01-26T22:21:12.545343Z",
    "market_id": "67284",
    "question": "Fed decision in March?",
    "from_regime": "High Confidence",
    "to_regime": "Active",
    "metrics_snapshot": {
      "nexus_score": 75.5,
      "macro_sensitivity": 0.0
    }
  },
  {
    "timestamp": "2026-01-26T22:21:12.545343Z",
    "market_id": "30615",
    "question": "2026 FIFA World Cup Winner ",
    "from_regime": "High Confidence",
    "to_regime": "Active",
    "metrics_snapshot": {
      "nexus_score": 79.8,
      "macro_sensitivity": 0.0
    }
  },
  {
    "timestamp": "2026-01-26T21:23:13.771476Z",
    "market_id": "175976",
    "question": "Elon Musk # tweets January 23 - January 30, 2026?",
    "from_regime": "Volatile",
    "to_regime": "Active",
    "metrics_snapshot": {
      "nexus_score": 58.9,
      "macro_sensitivity": 0.0
    }
  },
  {
    "timestamp": "2026-01-26T19:54:39.629610Z",
    "market_id": "133127",
    "question": "Will Israel strike Lebanon on...?",
    "from_regime": "Volatile",
    "to_regime": "Low Confidence",
    "metrics_snapshot": {
      "nexus_score": 34.3,
      "macro_sensitivity": 0.0
    }
  },
  {
    "timestamp": "2026-01-26T19:54:39.629610Z",
    "market_id": "148292",
    "question": "Will the US acquire part of Greenland in 2026?",
    "from_regime": "Active",
    "to_regime": "High Confidence",
    "metrics_snapshot": {
      "nexus_score": 80.2,
      "macro_sensitivity": 0.0
    }
  },
  {
    "timestamp": "2026-01-26T19:05:39.074438Z",
    "market_id": "125868",
    "question": "Will Silver (SI) hit__ by end of January?",
    "from_regime": "Volatile",
    "to_regime": "Active",
    "metrics_snapshot": {
      "nexus_score": 61.2,
      "macro_sensitivity": 0.0
    }
  },
  {
    "timestamp": "2026-01-26T17:46:59.311891Z",
    "market_id": "31759",
    "question": "Russia x Ukraine ceasefire by March 31, 2026?",
    "from_regime": "Active",
    "to_regime": "High Confidence",
    "metrics_snapshot": {
      "nexus_score": 80.6,
      "macro_sensitivity": 0.0
    }
  },
  {
    "timestamp": "2026-01-26T17:46:59.311891Z",
    "market_id": "27830",
    "question": "2026 NBA Champion",
    "from_regime": "High Confidence",
    "to_regime": "Active",
    "metrics_snapshot": {
      "nexus_score": 79.9,
      "macro_sensitivity": 0.0
    }
  },
  {
    "timestamp": "2026-01-26T15:54:36.585067Z",
    "market_id": "30615",
    "question": "2026 FIFA World Cup Winner ",
    "from_regime": "Active",
    "to_regime": "High Confidence",
    "metrics_snapshot": {
      "nexus_score": 80.0,
      "macro_sensitivity": 0.0
    }
  },
  {
    "timestamp": "2026-01-26T15:54:36.585067Z",
    "market_id": "27830",
    "question": "2026 NBA Champion",
    "from_regime": "Active",
    "to_regime": "High Confidence",
    "metrics_snapshot": {
      "nexus_score": 80.9,
      "macro_sensitivity": 0.0
    }
  },
  {
    "timestamp": "2026-01-26T14:48:59.750098Z",
    "market_id": "27830",
    "question": "2026 NBA Champion",
    "from_regime": "High Confidence",
    "to_regime": "Active",
    "metrics_snapshot": {
      "nexus_score": 77.8,
      "macro_sensitivity": 0.0
    }
  },
  {
    "timestamp": "2026-01-26T14:05:17.749680Z",
    "market_id": "137340",
    "question": "What price will Solana hit in January?",
    "from_regime": "Low Confidence",
    "to_regime": "Active",
    "metrics_snapshot": {
      "nexus_score": 57.8,
      "macro_sensitivity": 0.0
    }
  },
  {
    "timestamp": "2026-01-26T14:05:17.749680Z",
    "market_id": "31552",
    "question": "Presidential Election Winner 2028",
    "from_regime": "High Confidence",
    "to_regime": "Active",
    "metrics_snapshot": {
      "nexus_score": 79.7,
      "macro_sensitivity": 0.0
    }
  },
  {
    "timestamp": "2026-01-26T12:44:40.868372Z",
    "market_id": "137340",
    "question": "What price will Solana hit in January?",
    "from_regime": "Active",
    "to_regime": "Low Confidence",
    "metrics_snapshot": {
      "nexus_score": 37.8,
      "macro_sensitivity": 0.0
    }
  },
  {
    "timestamp": "2026-01-26T12:44:40.868372Z",
    "market_id": "30615",
    "question": "2026 FIFA World Cup Winner ",
    "from_regime": "High Confidence",
    "to_regime": "Active",
    "metrics_snapshot": {
      "nexus_score": 79.7,
      "macro_sensitivity": 0.0
    }
  },
  {
    "timestamp": "2026-01-26T11:43:16.983706Z",
    "market_id": "30615",
    "question": "2026 FIFA World Cup Winner ",
    "from_regime": "Active",
    "to_regime": "High Confidence",
    "metrics_snapshot": {
      "nexus_score": 80.0,
      "macro_sensitivity": 0.0
    }
  },
  {
    "timestamp": "2026-01-26T11:20:22.550876Z",
    "market_id": "30615",
    "question": "2026 FIFA World Cup Winner ",
    "from_regime": "High Confidence",
    "to_regime": "Active",
    "metrics_snapshot": {
      "nexus_score": 79.8,
      "macro_sensitivity": 0.0
    }
  },
  {
    "timestamp": "2026-01-26T10:53:20.030954Z",
    "market_id": "30615",
    "question": "2026 FIFA World Cup Winner ",
    "from_regime": "Active",
    "to_regime": "High Confidence",
    "metrics_snapshot": {
      "nexus_score": 80.0,
      "macro_sensitivity": 0.0
    }
  },
  {
    "timestamp": "2026-01-26T10:25:27.654326Z",
    "market_id": "30828",
    "question": "Xi Jinping out before 2027?",
    "from_regime": "Active",
    "to_regime": "High Confidence",
    "metrics_snapshot": {
      "nexus_score": 84.7,
      "macro_sensitivity": 0.0
    }
  },
  {
    "timestamp": "2026-01-26T09:50:02.361895Z",
    "market_id": "27830",
    "question": "2026 NBA Champion",
    "from_regime": "Active",
    "to_regime": "High Confidence",
    "metrics_snapshot": {
      "nexus_score": 81.7,
      "macro_sensitivity": 0.0
    }
  },
  {
    "timestamp": "2026-01-26T09:01:40.658620Z",
    "market_id": "34044",
    "question": "Will China invade Taiwan by end of 2026?",
    "from_regime": "High Confidence",
    "to_regime": "Active",
    "metrics_snapshot": {
      "nexus_score": 79.8,
      "macro_sensitivity": 0.0
    }
  },
  {
    "timestamp": "2026-01-26T08:31:17.617485Z",
    "market_id": "159840",
    "question": "US next strikes Iran on...?",
    "from_regime": "Volatile",
    "to_regime": "High Confidence",
    "metrics_snapshot": {
      "nexus_score": 90.3,
      "macro_sensitivity": 0.0
    }
  },
  {
    "timestamp": "2026-01-26T08:31:17.617485Z",
    "market_id": "30829",
    "question": "Democratic Presidential Nominee 2028",
    "from_regime": "Active",
    "to_regime": "High Confidence",
    "metrics_snapshot": {
      "nexus_score": 80.3,
      "macro_sensitivity": 0.0
    }
  },
  {
    "timestamp": "2026-01-26T07:49:08.286422Z",
    "market_id": "84841",
    "question": "Epstein blackmail evidence released by...? ",
    "from_regime": "High Confidence",
    "to_regime": "Active",
    "metrics_snapshot": {
      "nexus_score": 79.8,
      "macro_sensitivity": 0.0
    }
  },
  {
    "timestamp": "2026-01-26T07:27:30.519864Z",
    "market_id": "30615",
    "question": "2026 FIFA World Cup Winner ",
    "from_regime": "High Confidence",
    "to_regime": "Active",
    "metrics_snapshot": {
      "nexus_score": 79.8,
      "macro_sensitivity": 0.0
    }
  },
  {
    "timestamp": "2026-01-26T07:27:30.519864Z",
    "market_id": "27830",
    "question": "2026 NBA Champion",
    "from_regime": "High Confidence",
    "to_regime": "Active",
    "metrics_snapshot": {
      "nexus_score": 78.5,
      "macro_sensitivity": 0.0
    }
  },
  {
    "timestamp": "2026-01-26T07:27:30.519864Z",
    "market_id": "30829",
    "question": "Democratic Presidential Nominee 2028",
    "from_regime": "High Confidence",
    "to_regime": "Active",
    "metrics_snapshot": {
      "nexus_score": 79.8,
      "macro_sensitivity": 0.0
    }
  },
  {
    "timestamp": "2026-01-26T06:52:08.610551Z",
    "market_id": "30615",
    "question": "2026 FIFA World Cup Winner ",
    "from_regime": "Active",
    "to_regime": "High Confidence",
    "metrics_snapshot": {
      "nexus_score": 80.3,
      "macro_sensitivity": 0.0
    }
  },
  {
    "timestamp": "2026-01-26T05:32:54.114779Z",
    "market_id": "30829",
    "question": "Democratic Presidential Nominee 2028",
    "from_regime": "Active",
    "to_regime": "High Confidence",
    "metrics_snapshot": {
      "nexus_score": 80.4,
      "macro_sensitivity": 0.0
    }
  },
  {
    "timestamp": "2026-01-26T04:55:49.837764Z",
    "market_id": "119872",
    "question": "2026 Men's Australian Open Winner",
    "from_regime": "High Confidence",
    "to_regime": "Active",
    "metrics_snapshot": {
      "nexus_score": 76.7,
      "macro_sensitivity": 0.0
    }
  },
  {
    "timestamp": "2026-01-26T03:56:22.309435Z",
    "market_id": "125868",
    "question": "Will Silver (SI) hit__ by end of January?",
    "from_regime": "Low Confidence",
    "to_regime": "Volatile",
    "metrics_snapshot": {
      "nexus_score": 46.3,
      "macro_sensitivity": 0.0
    }
  },
  {
    "timestamp": "2026-01-26T03:56:22.309435Z",
    "market_id": "30828",
    "question": "Xi Jinping out before 2027?",
    "from_regime": "High Confidence",
    "to_regime": "Active",
    "metrics_snapshot": {
      "nexus_score": 78.6,
      "macro_sensitivity": 0.0
    }
  },
  {
    "timestamp": "2026-01-26T03:56:22.309435Z",
    "market_id": "137340",
    "question": "What price will Solana hit in January?",
    "from_regime": "Low Confidence",
    "to_regime": "Active",
    "metrics_snapshot": {
      "nexus_score": 65.4,
      "macro_sensitivity": 0.0
    }
  },
  {
    "timestamp": "2026-01-26T03:56:22.309435Z",
    "market_id": "30615",
    "question": "2026 FIFA World Cup Winner ",
    "from_regime": "High Confidence",
    "to_regime": "Active",
    "metrics_snapshot": {
      "nexus_score": 79.6,
      "macro_sensitivity": 0.0
    }
  }
]